albumoftheyearapi/__init__.py
albumoftheyearapi/album.py
albumoftheyearapi/artist.py
albumoftheyearapi/client.py
albumoftheyearapi/user.py
album_of_the_year_api-0.2.10.dist-info/METADATA
album_of_the_year_api-0.2.10.dist-info/WHEEL
album_of_the_year_api-0.2.10.dist-info/top_level.txt
album_of_the_year_api-0.2.10.dist-info/RECORD
