Metadata-Version: 2.1
Name: album-of-the-year-api
Version: 0.2.10
Summary: A light weight Python library that acts as an API for the website albumoftheyear.org
Home-page: https://github.com/JahsiasWhite/AlbumOfTheYearWrapper
Author: Jahsias White
Author-email: jahsias.white@gmail.com
License: GNU
Requires-Dist: pytest==7.0.1
Requires-Dist: SQLAlchemy==1.3.22
Requires-Dist: bs4==0.0.1
Requires-Dist: urllib3==1.26.8
